ufmetadata/__init__.py
ufmetadata/assets.py
ufmetadata-0.0.2.dist-info/LICENSE
ufmetadata-0.0.2.dist-info/METADATA
ufmetadata-0.0.2.dist-info/WHEEL
ufmetadata-0.0.2.dist-info/top_level.txt
ufmetadata-0.0.2.dist-info/RECORD
