Metadata-Version: 2.1
Name: ufmetadata
Version: 0.0.2
Summary: Urban Flows Observatory (Sheffield) metadata tools
Home-page: https://github.com/Joe-Heffer-Shef/ufmetadata
Author: Joe Heffer
Author-email: j.heffer@sheffield.ac.uk
License: UNKNOWN
Platform: UNKNOWN
Classifier: Programming Language :: Python :: 3
Classifier: License :: OSI Approved :: MIT License
Classifier: Operating System :: OS Independent
